{
  "date": "2026-04-23",
  "articles": [
    {
      "id": "1",
      "title": "제3회 순직의무군경의 날 기념식 내일 서울현충원서 거행",
      "summary": "(서울=연합뉴스) 이정현 기자 = 국가보훈부는 병역의무를 이행하다 순직한 젊은이들을 추모하기 위한 '제3회 순직의무군경의 날 기념식'을 오는 2...",
      "category": "domestic",
      "source": "연합뉴스",
      "sourceUrl": "https://www.yna.co.kr/view/AKR20260423030800504",
      "publishedAt": "2026-04-23T08:42:09+09:00"
    },
    {
      "id": "2",
      "title": "[게시판] 중견련, 중견기업 현장 방문해 제도·정책 건의 청취",
      "summary": "▲ 한국중견기업연합회(중견련)는 중견기업의 경영 환경 개선을 위해 '회원사 현장 방문 프로젝트'를 시작한다고 23일 밝혔다. 사무국 직원들이 2...",
      "category": "economy",
      "source": "연합뉴스",
      "sourceUrl": "https://www.yna.co.kr/view/AKR20260423034300003",
      "publishedAt": "2026-04-23T08:56:36+09:00"
    },
    {
      "id": "3",
      "title": "월가 아인슈타인 \"시장, 이란서 완전히 벗어나…변수는 유가뿐\"",
      "summary": "(뉴욕=연합뉴스) 김연숙 특파원 = 미국 뉴욕증권거래소(NYSE)에서 40년 이상 현장을 지킨 베테랑 트레이더 피터 터크먼은 이란 전쟁의 시장 ...",
      "category": "world",
      "source": "연합뉴스",
      "sourceUrl": "https://www.yna.co.kr/view/AKR20260423025200072",
      "publishedAt": "2026-04-23T08:54:11+09:00"
    }
  ]
}
