{
  "date": "2026-06-04",
  "articles": [
    {
      "id": "1",
      "title": "6·3 지방선거 민주당 압승…시도지사 16곳 중 대부분 석권",
      "summary": "제9회 전국동시지방선거 개표 결과 더불어민주당이 16개 광역단체장 선거구 대부분에서 우세를 점했다. 전국 최종 투표율은 61.0%로 집계됐으며, 서울·경기 등 수도권 주요 광역단체장직도 민주당이 차지했다. 국민의힘은 광역단체장 1곳에서만 우위를 기록하는 참패를 당했다.",
      "category": "domestic",
      "source": "연합뉴스",
      "sourceUrl": "https://www.yna.co.kr/news",
      "publishedAt": "2026-06-04T06:00:00+09:00"
    },
    {
      "id": "2",
      "title": "부산 북갑 보선, 무소속 한동훈 42.96% 득표…민주당 하정우 석패",
      "summary": "부산 북갑 국회의원 보궐선거에서 무소속 한동훈 후보가 42.96%를 득표해, 41.26%를 얻은 더불어민주당 하정우 후보를 1.7%포인트 차로 꺾었다. 야권 단일화 무산으로 3자 대결이 치러졌으나 보수표가 한동훈 후보로 집결하며 역전됐다. 하정우 후보는 '악수 후 손 털기' 논란 등 선거 초반 실수와 AI 스타트업 주식 논란 등이 패인으로 분석된다.",
      "category": "domestic",
      "source": "연합뉴스",
      "sourceUrl": "https://www.yna.co.kr/view/AKR20260604063700051",
      "publishedAt": "2026-06-04T08:56:00+09:00"
    },
    {
      "id": "3",
      "title": "한미 통상본부장-USTR 면담…\"한국산 12.5% 관세 합의 이익균형 유지해야\"",
      "summary": "여한구 산업통상부 통상교섭본부장이 파리 OECD 각료이사회를 계기로 제이미슨 그리어 USTR 대표와 면담하고, 미국이 강제노동 생산제품 수입금지 무역법 301조를 근거로 한국산 제품에 12.5% 관세를 부과하기로 한 것에 대해 기존 한미 관세 합의에 따른 이익 균형 유지의 중요성을 강조했다. 미 연방대법원이 트럼프 상호관세를 위법 판결한 직후 대체 카드로 활용된 조치다.",
      "category": "economy",
      "source": "연합뉴스",
      "sourceUrl": "https://www.yna.co.kr/view/AKR20260604063400003",
      "publishedAt": "2026-06-04T08:55:00+09:00"
    }
  ]
}
